{
    "type": "object",
    "anyOf": [
        {
            "required": [
                "path",
                "set"
            ]
        },
        {
            "required": [
                "path",
                "contains"
            ]
        },
        {
            "required": [
                "path",
                "not contains"
            ]
        },
        {
            "required": [
                "path",
                "is"
            ]
        },
        {
            "required": [
                "path",
                "is not"
            ]
        },
        {
            "required": [
                "path",
                "matches"
            ]
        },
        {
            "required": [
                "path",
                "not matches"
            ]
        },
        {
            "required": [
                "path",
                "count"
            ]
        }
    ],
    "additionalProperties": false,
    "properties": {
        "set": {
            "$ref": "#/definitions/value_set"
        },
        "path": {
            "$ref": "#/definitions/path_path"
        },
        "contains": {
            "$ref": "#/definitions/contains"
        },
        "not contains": {
            "$ref": "#/definitions/contains"
        },
        "is": {
            "$ref": "#/definitions/equals"
        },
        "is not": {
            "$ref": "#/definitions/equals"
        },
        "matches": {
            "$ref": "#/definitions/matches"
        },
        "not matches": {
            "$ref": "#/definitions/matches"
        },
        "count": {
            "$ref": "#/definitions/count_count"
        }
    }
}
